edubotics_core/__init__.py
edubotics_core/chat/__init__.py
edubotics_core/chat/base.py
edubotics_core/chat/chat_model_loader.py
edubotics_core/chat/helpers.py
edubotics_core/chat/llm_tutor.py
edubotics_core/chat/langchain/__init__.py
edubotics_core/chat/langchain/langchain_rag.py
edubotics_core/chat/langchain/utils.py
edubotics_core/chat_processor/__init__.py
edubotics_core/chat_processor/helpers.py
edubotics_core/chat_processor/literal_ai.py
edubotics_core/config/__init__.py
edubotics_core/config/constants.py
edubotics_core/dataloader/__init__.py
edubotics_core/dataloader/data_loader.py
edubotics_core/dataloader/helpers.py
edubotics_core/dataloader/metadata_extractor.py
edubotics_core/dataloader/webpage_crawler.py
edubotics_core/dataloader/pdf_readers/__init__.py
edubotics_core/dataloader/pdf_readers/base.py
edubotics_core/dataloader/pdf_readers/gpt.py
edubotics_core/dataloader/pdf_readers/llama.py
edubotics_core/dataloader/repo_readers/__init__.py
edubotics_core/dataloader/repo_readers/github.py
edubotics_core/dataloader/repo_readers/helpers.py
edubotics_core/retriever/__init__.py
edubotics_core/retriever/base.py
edubotics_core/retriever/chroma_retriever.py
edubotics_core/retriever/colbert_retriever.py
edubotics_core/retriever/faiss_retriever.py
edubotics_core/retriever/helpers.py
edubotics_core/retriever/raptor_retriever.py
edubotics_core/retriever/retriever.py
edubotics_core/vectorstore/__init__.py
edubotics_core/vectorstore/base.py
edubotics_core/vectorstore/chroma.py
edubotics_core/vectorstore/colbert.py
edubotics_core/vectorstore/embedding_model_loader.py
edubotics_core/vectorstore/faiss.py
edubotics_core/vectorstore/helpers.py
edubotics_core/vectorstore/raptor.py
edubotics_core/vectorstore/store_manager.py
edubotics_core/vectorstore/vectorstore.py
edubotics_core-0.1.8.dist-info/licenses/LICENSE
edubotics_core-0.1.8.dist-info/METADATA
edubotics_core-0.1.8.dist-info/WHEEL
edubotics_core-0.1.8.dist-info/entry_points.txt
edubotics_core-0.1.8.dist-info/top_level.txt
edubotics_core-0.1.8.dist-info/RECORD
